CHANGELOG.md
LICENSE
german_nouns/config.py
german_nouns/index.txt
german_nouns/lookup/__init__.py
german_nouns/lookup/examples.py
german_nouns/nouns.csv
german_nouns/parse_dump/__main__.py
german_nouns/parse_dump/extend_flexion.py
german_nouns-1.2.5.dist-info/LICENSE
german_nouns-1.2.5.dist-info/WHEEL
german_nouns-1.2.5.dist-info/METADATA
german_nouns-1.2.5.dist-info/RECORD
