Metadata-Version: 2.1
Name: german-nouns
Version: 1.2.5
Summary: A list of ~100,000 German nouns and their grammatical properties compiled from WiktionaryDE as CSV file. Plus a module to look up the data and parse compound words.
Home-page: https://github.com/gambolputty/german-nouns
License: CC BY-SA 4.0
Keywords: german,nouns,words,compound words,lookup,wiktionary,nlp
Author: Gregor Weichbrodt
Author-email: gregorweichbrodt@gmail.com
Requires-Python: >=3.8,<4.0
Classifier: License :: Other/Proprietary License
Classifier: Natural Language :: German
Classifier: Operating System :: OS Independent
Classifier: Programming Language :: Python :: 3
Classifier: Programming Language :: Python :: 3.10
Classifier: Programming Language :: Python :: 3.8
Classifier: Programming Language :: Python :: 3.9
Classifier: Topic :: Text Processing
Requires-Dist: wiktionary-de-parser (>=0.9.2,<0.10.0)
Project-URL: Repository, https://github.com/gambolputty/german-nouns
